{
  "kind": "collectionType",
  "collectionName": "websites",
  "info": {
    "singularName": "website",
    "pluralName": "websites",
    "displayName": "Website",
    "description": ""
  },
  "options": {
    "draftAndPublish": false,
    "privateAttributes": [
      "createdAt",
      "updatedAt"
    ]
  },
  "pluginOptions": {},
  "attributes": {
    "name": {
      "type": "string",
      "required": true
    },
    "link": {
      "type": "string",
      "required": true
    },
    "logo": {
      "type": "media",
      "multiple": false,
      "required": false,
      "allowedTypes": [
        "images"
      ]
    }
  }
}